{
  "slug": "hsk4-interview-tips",
  "level": 4,
  "title_zh": "面试技巧",
  "title_py": "Miànshì jìqiǎo",
  "title_en": "Interview Tips",
  "audio": null,
  "sentences": [
    {
      "t": [
        ["找", "zhǎo", "to look for"],
        ["工作", "gōngzuò", "job"],
        ["的", "de", "(possessive)"],
        ["时候", "shíhou", "time; when"],
        ["，"],
        ["面试", "miànshì", "interview"],
        ["常常", "chángcháng", "often"],
        ["比", "bǐ", "compared to"],
        ["简历", "jiǎnlì", "resume"],
        ["更", "gèng", "more"],
        ["重要", "zhòngyào", "important"],
        ["。"]
      ],
      "en": "When looking for a job, the interview is often more important than the resume."
    },
    {
      "t": [
        ["很多", "hěn duō", "many"],
        ["人", "rén", "people"],
        ["能力", "nénglì", "ability"],
        ["不错", "búcuò", "quite good"],
        ["，"],
        ["却", "què", "yet; however"],
        ["因为", "yīnwèi", "because"],
        ["太", "tài", "too"],
        ["紧张", "jǐnzhāng", "nervous"],
        ["，"],
        ["面试", "miànshì", "interview"],
        ["的", "de", "(possessive)"],
        ["时候", "shíhou", "time; when"],
        ["一", "yí", "one"],
        ["句", "jù", "(measure for sentences)"],
        ["话", "huà", "words"],
        ["也", "yě", "also"],
        ["说", "shuō", "to speak"],
        ["不好", "bù hǎo", "not well"],
        ["。"]
      ],
      "en": "Many people are quite capable, yet because they get too nervous, they can't get a single sentence out well in the interview."
    },
    {
      "t": [
        ["其实", "qíshí", "actually"],
        ["，"],
        ["面试", "miànshì", "interview"],
        ["是", "shì", "is"],
        ["有", "yǒu", "to have"],
        ["技巧", "jìqiǎo", "technique; skill"],
        ["的", "de", "(particle)"],
        ["。"]
      ],
      "en": "Actually, there are techniques to interviewing."
    },
    {
      "t": [
        ["首先", "shǒuxiān", "first of all"],
        ["，"],
        ["去", "qù", "to go"],
        ["之前", "zhīqián", "before"],
        ["要", "yào", "should"],
        ["了解", "liǎojiě", "to understand"],
        ["这", "zhè", "this"],
        ["家", "jiā", "(measure for companies)"],
        ["公司", "gōngsī", "company"],
        ["，"],
        ["知道", "zhīdào", "to know"],
        ["他们", "tāmen", "they"],
        ["需要", "xūyào", "to need"],
        ["什么样", "shénmeyàng", "what kind"],
        ["的", "de", "(possessive)"],
        ["人", "rén", "person"],
        ["。"]
      ],
      "en": "First, before you go, learn about the company and find out what kind of person they need."
    },
    {
      "t": [
        ["其次", "qícì", "secondly"],
        ["，"],
        ["回答", "huídá", "to answer"],
        ["问题", "wèntí", "questions"],
        ["的", "de", "(possessive)"],
        ["时候", "shíhou", "time; when"],
        ["，"],
        ["不要", "búyào", "don't"],
        ["只", "zhǐ", "only"],
        ["说", "shuō", "to say"],
        ["“"],
        ["我", "wǒ", "I"],
        ["很", "hěn", "very"],
        ["努力", "nǔlì", "hardworking"],
        ["”"],
        ["，"],
        ["最好", "zuìhǎo", "had better"],
        ["举", "jǔ", "to give (an example)"],
        ["一", "yí", "one"],
        ["个", "ge", "(measure word)"],
        ["真实", "zhēnshí", "real; true"],
        ["的", "de", "(possessive)"],
        ["例子", "lìzi", "example"],
        ["。"]
      ],
      "en": "Second, when answering questions, don't just say \"I work very hard\" — it's best to give a real example."
    },
    {
      "t": [
        ["另外", "lìngwài", "in addition"],
        ["，"],
        ["穿", "chuān", "to dress"],
        ["得", "de", "(degree particle)"],
        ["干净", "gānjìng", "clean; neat"],
        ["一点儿", "yìdiǎnr", "a little"],
        ["，"],
        ["早", "zǎo", "early"],
        ["到", "dào", "to arrive"],
        ["十", "shí", "ten"],
        ["分钟", "fēnzhōng", "minutes"],
        ["，"],
        ["这些", "zhèxiē", "these"],
        ["小事", "xiǎoshì", "small things"],
        ["都", "dōu", "all"],
        ["会", "huì", "will"],
        ["给", "gěi", "to give"],
        ["人", "rén", "people"],
        ["好", "hǎo", "good"],
        ["印象", "yìnxiàng", "impression"],
        ["。"]
      ],
      "en": "In addition, dress neatly and arrive ten minutes early — these small things all leave a good impression."
    },
    {
      "t": [
        ["最后", "zuìhòu", "finally"],
        ["别", "bié", "don't"],
        ["忘", "wàng", "to forget"],
        ["了", "le", "(particle)"],
        ["："],
        ["面试", "miànshì", "interview"],
        ["不仅", "bùjǐn", "not only"],
        ["是", "shì", "is"],
        ["公司", "gōngsī", "company"],
        ["在", "zài", "(progressive)"],
        ["选", "xuǎn", "to choose"],
        ["你", "nǐ", "you"],
        ["，"],
        ["而且", "érqiě", "but also"],
        ["是", "shì", "is"],
        ["你", "nǐ", "you"],
        ["在", "zài", "(progressive)"],
        ["选", "xuǎn", "to choose"],
        ["公司", "gōngsī", "company"],
        ["。"]
      ],
      "en": "Finally, don't forget: an interview is not only the company choosing you, but also you choosing the company."
    },
    {
      "t": [
        ["放松", "fàngsōng", "to relax"],
        ["一点儿", "yìdiǎnr", "a little"],
        ["，"],
        ["把", "bǎ", "(object marker)"],
        ["面试", "miànshì", "interview"],
        ["当成", "dàngchéng", "to treat as"],
        ["一", "yí", "one"],
        ["次", "cì", "(measure for occurrences)"],
        ["聊天", "liáotiān", "chat"],
        ["，"],
        ["你", "nǐ", "you"],
        ["会", "huì", "will"],
        ["做", "zuò", "to do"],
        ["得", "de", "(degree particle)"],
        ["更", "gèng", "even"],
        ["好", "hǎo", "better"],
        ["。"]
      ],
      "en": "Relax a little, treat the interview as a chat, and you will do even better."
    }
  ],
  "vocab": [
    ["面试", "miànshì", "interview"],
    ["技巧", "jìqiǎo", "technique; skill"],
    ["简历", "jiǎnlì", "resume"],
    ["印象", "yìnxiàng", "impression"],
    ["真实", "zhēnshí", "real; true"],
    ["当成", "dàngchéng", "to treat as"]
  ],
  "quiz": [
    {
      "q": "According to the text, what is often more important than the resume?",
      "a": ["The interview", "Your university", "Knowing someone at the company"],
      "c": 0
    },
    {
      "q": "When answering questions, what should you do instead of just saying \"I work very hard\"?",
      "a": ["Talk about your salary expectations", "Give a real example", "Ask the interviewer a question back"],
      "c": 1
    },
    {
      "q": "What does the author say an interview really is?",
      "a": ["A test that only the company controls", "A chance to show how nervous you are", "Both the company choosing you and you choosing the company"],
      "c": 2
    }
  ],
  "grammar": [
    {
      "p": "首先……其次……另外……最后……",
      "e": "A set of connectors for listing points in order: 首先 (first), 其次 (second), 另外 (in addition), 最后 (finally). The text uses them to organize the interview tips.",
      "x": "首先要多听，其次要多说，另外还要多写。— First listen more, second speak more, and in addition write more."
    },
    {
      "p": "不仅……而且……",
      "e": "\"Not only A, but also B\" joins two related points, the second often more important: 面试不仅是公司在选你，而且是你在选公司。",
      "x": "运动不仅对身体好，而且让人心情好。— Exercise is not only good for the body, but also lifts your mood."
    }
  ]
}
