{
  "slug": "hsk5-involution-and-lying-flat",
  "level": 5,
  "title_zh": "内卷与躺平",
  "title_py": "Nèijuǎn yǔ tǎngpíng",
  "title_en": "Involution and Lying Flat",
  "audio": null,
  "sentences": [
    {
      "t": [
        ["如果", "rúguǒ", "if"],
        ["你", "nǐ", "you"],
        ["想", "xiǎng", "to want"],
        ["了解", "liǎojiě", "to understand"],
        ["今天", "jīntiān", "today"],
        ["的", "de", "(possessive)"],
        ["中国", "Zhōngguó", "China"],
        ["年轻人", "niánqīngrén", "young people"],
        ["，"],
        ["有", "yǒu", "there are"],
        ["两", "liǎng", "two"],
        ["个", "ge", "(measure word)"],
        ["词", "cí", "word"],
        ["你", "nǐ", "you"],
        ["一定", "yídìng", "definitely"],
        ["要", "yào", "must"],
        ["认识", "rènshi", "to know"],
        ["："],
        ["“"],
        ["内卷", "nèijuǎn", "involution — pointless internal competition"],
        ["”"],
        ["和", "hé", "and"],
        ["“"],
        ["躺平", "tǎngpíng", "lying flat — opting out of the rat race"],
        ["”"],
        ["。"]
      ],
      "en": "If you want to understand young people in China today, there are two words you must know: neijuan (involution) and tangping (lying flat)."
    },
    {
      "t": [
        ["“"],
        ["内卷", "nèijuǎn", "involution"],
        ["”"],
        ["指", "zhǐ", "to refer to"],
        ["的", "de", "(particle)"],
        ["是", "shì", "to be"],
        ["一", "yì", "one"],
        ["种", "zhǒng", "kind"],
        ["没有", "méiyǒu", "without"],
        ["意义", "yìyì", "meaning"],
        ["的", "de", "(possessive)"],
        ["竞争", "jìngzhēng", "competition"],
        ["："],
        ["大家", "dàjiā", "everyone"],
        ["越来越", "yuèláiyuè", "more and more"],
        ["努力", "nǔlì", "hardworking"],
        ["，"],
        ["得到", "dédào", "to obtain"],
        ["的", "de", "(particle)"],
        ["却", "què", "however"],
        ["没有", "méiyǒu", "not"],
        ["变", "biàn", "to become"],
        ["多", "duō", "more"],
        ["。"]
      ],
      "en": "\"Involution\" refers to a kind of meaningless competition: everyone works harder and harder, yet what they get does not increase."
    },
    {
      "t": [
        ["比如", "bǐrú", "for example"],
        ["在", "zài", "at"],
        ["有些", "yǒuxiē", "some"],
        ["公司", "gōngsī", "company"],
        ["，"],
        ["一", "yí", "one"],
        ["个", "ge", "(measure word)"],
        ["人", "rén", "person"],
        ["主动", "zhǔdòng", "voluntarily"],
        ["加班", "jiābān", "to work overtime"],
        ["，"],
        ["其他人", "qítā rén", "other people"],
        ["也", "yě", "also"],
        ["不得不", "bùdébù", "to have no choice but"],
        ["跟着", "gēnzhe", "to follow"],
        ["加班", "jiābān", "to work overtime"],
        ["，"],
        ["结果", "jiéguǒ", "as a result"],
        ["所有人", "suǒyǒu rén", "everyone"],
        ["都", "dōu", "all"],
        ["更", "gèng", "more"],
        ["累", "lèi", "tired"],
        ["，"],
        ["工资", "gōngzī", "salary"],
        ["却", "què", "however"],
        ["一", "yì", "one"],
        ["分", "fēn", "cent"],
        ["没", "méi", "not"],
        ["涨", "zhǎng", "to rise"],
        ["。"]
      ],
      "en": "For example, in some companies one person volunteers to work overtime, so everyone else has no choice but to follow; in the end everyone is more exhausted, yet salaries haven't risen a cent."
    },
    {
      "t": [
        ["“"],
        ["躺平", "tǎngpíng", "lying flat"],
        ["”"],
        ["是", "shì", "to be"],
        ["对", "duì", "toward"],
        ["内卷", "nèijuǎn", "involution"],
        ["的", "de", "(possessive)"],
        ["回答", "huídá", "answer"],
        ["："],
        ["既然", "jìrán", "since"],
        ["努力", "nǔlì", "to work hard"],
        ["没有", "méiyǒu", "not have"],
        ["用", "yòng", "use"],
        ["，"],
        ["那", "nà", "then"],
        ["我", "wǒ", "I"],
        ["就", "jiù", "then"],
        ["降低", "jiàngdī", "to lower"],
        ["欲望", "yùwàng", "desire"],
        ["，"],
        ["不", "bù", "not"],
        ["买", "mǎi", "to buy"],
        ["房", "fáng", "house"],
        ["，"],
        ["不", "bù", "not"],
        ["结婚", "jiéhūn", "to marry"],
        ["，"],
        ["只", "zhǐ", "only"],
        ["做", "zuò", "to do"],
        ["最", "zuì", "most"],
        ["基本", "jīběn", "basic"],
        ["的", "de", "(possessive)"],
        ["工作", "gōngzuò", "work"],
        ["。"]
      ],
      "en": "\"Lying flat\" is the answer to involution: since hard work is useless, I will lower my desires — no buying a house, no getting married, just doing the most basic work."
    },
    {
      "t": [
        ["我", "wǒ", "my"],
        ["表弟", "biǎodì", "younger cousin"],
        ["就", "jiù", "exactly"],
        ["是", "shì", "to be"],
        ["这样", "zhèyàng", "like this"],
        ["，"],
        ["他", "tā", "he"],
        ["说", "shuō", "to say"],
        ["："],
        ["“"],
        ["与其", "yǔqí", "rather than"],
        ["在", "zài", "in"],
        ["大", "dà", "big"],
        ["城市", "chéngshì", "city"],
        ["继续", "jìxù", "to continue"],
        ["竞争", "jìngzhēng", "to compete"],
        ["，"],
        ["不如", "bùrú", "better to"],
        ["回", "huí", "to return"],
        ["老家", "lǎojiā", "hometown"],
        ["过", "guò", "to live"],
        ["安静", "ānjìng", "quiet"],
        ["的", "de", "(possessive)"],
        ["日子", "rìzi", "days; life"],
        ["。"],
        ["”"]
      ],
      "en": "My cousin is exactly like this. He says: \"Rather than keep competing in a big city, I'd rather go back to my hometown and live a quiet life.\""
    },
    {
      "t": [
        ["父母", "fùmǔ", "parents"],
        ["那", "nà", "that"],
        ["一", "yí", "one"],
        ["代", "dài", "generation"],
        ["批评", "pīpíng", "to criticize"],
        ["这", "zhè", "this"],
        ["种", "zhǒng", "kind"],
        ["态度", "tàidu", "attitude"],
        ["太", "tài", "too"],
        ["消极", "xiāojí", "negative; passive"],
        ["，"],
        ["可", "kě", "but"],
        ["年轻人", "niánqīngrén", "young people"],
        ["觉得", "juéde", "to feel"],
        ["，"],
        ["这", "zhè", "this"],
        ["不是", "bú shì", "is not"],
        ["懒", "lǎn", "lazy"],
        ["，"],
        ["而是", "érshì", "but rather"],
        ["一", "yì", "one"],
        ["种", "zhǒng", "kind"],
        ["清醒", "qīngxǐng", "clear-headedness"],
        ["。"]
      ],
      "en": "Their parents' generation criticizes this attitude as too negative, but young people feel it is not laziness — it is a kind of clear-headedness."
    },
    {
      "t": [
        ["有意思", "yǒu yìsi", "interesting"],
        ["的", "de", "(particle)"],
        ["是", "shì", "to be"],
        ["，"],
        ["很多", "hěn duō", "many"],
        ["说", "shuō", "to say"],
        ["要", "yào", "to want"],
        ["躺平", "tǎngpíng", "to lie flat"],
        ["的", "de", "(particle)"],
        ["人", "rén", "people"],
        ["，"],
        ["第二天", "dì-èr tiān", "the next day"],
        ["还是", "háishi", "still"],
        ["准时", "zhǔnshí", "on time"],
        ["去", "qù", "to go"],
        ["上班", "shàngbān", "to go to work"],
        ["了", "le", "(particle)"],
        ["。"]
      ],
      "en": "The interesting thing is, many people who say they are going to lie flat still show up to work on time the next day."
    },
    {
      "t": [
        ["也许", "yěxǔ", "perhaps"],
        ["躺平", "tǎngpíng", "lying flat"],
        ["更", "gèng", "more"],
        ["像", "xiàng", "to be like"],
        ["一", "yì", "one"],
        ["种", "zhǒng", "kind"],
        ["情绪", "qíngxù", "mood; emotion"],
        ["，"],
        ["一", "yì", "one"],
        ["种", "zhǒng", "kind"],
        ["在", "zài", "under"],
        ["压力", "yālì", "pressure"],
        ["下", "xià", "under"],
        ["保护", "bǎohù", "to protect"],
        ["自己", "zìjǐ", "oneself"],
        ["的", "de", "(possessive)"],
        ["方式", "fāngshì", "way"],
        ["。"]
      ],
      "en": "Perhaps lying flat is more like a mood — a way of protecting oneself under pressure."
    },
    {
      "t": [
        ["完全", "wánquán", "completely"],
        ["躺平", "tǎngpíng", "to lie flat"],
        ["的", "de", "(particle)"],
        ["人", "rén", "people"],
        ["是", "shì", "to be"],
        ["少数", "shǎoshù", "minority"],
        ["，"],
        ["大部分", "dàbùfen", "most"],
        ["人", "rén", "people"],
        ["都", "dōu", "all"],
        ["在", "zài", "at"],
        ["内卷", "nèijuǎn", "involution"],
        ["和", "hé", "and"],
        ["躺平", "tǎngpíng", "lying flat"],
        ["之间", "zhījiān", "between"],
        ["，"],
        ["寻找", "xúnzhǎo", "to search for"],
        ["自己", "zìjǐ", "oneself"],
        ["能", "néng", "can"],
        ["接受", "jiēshòu", "to accept"],
        ["的", "de", "(possessive)"],
        ["位置", "wèizhi", "position"],
        ["。"]
      ],
      "en": "Those who completely lie flat are a minority; most people are somewhere between involution and lying flat, searching for a position they can accept."
    }
  ],
  "vocab": [
    ["内卷", "nèijuǎn", "involution — competition where everyone works harder but no one gains"],
    ["躺平", "tǎngpíng", "lying flat — opting out of the rat race"],
    ["欲望", "yùwàng", "desire"],
    ["清醒", "qīngxǐng", "clear-headed; sober"],
    ["消极", "xiāojí", "negative; passive"],
    ["竞争", "jìngzhēng", "competition; to compete"]
  ],
  "quiz": [
    {
      "q": "According to the text, what does 'involution' (neijuan) describe?",
      "a": [
        "Meaningless competition where everyone works harder but gains nothing more",
        "A government policy that limits overtime work",
        "Young people moving from villages to big cities"
      ],
      "c": 0
    },
    {
      "q": "What does the text observe about many people who say they will 'lie flat'?",
      "a": [
        "They quit their jobs within a week",
        "They still go to work on time the next day",
        "They move back to their hometowns immediately"
      ],
      "c": 1
    },
    {
      "q": "What did the narrator's cousin decide to do?",
      "a": [
        "Work overtime to earn a promotion in the big city",
        "Borrow money to buy an apartment before getting married",
        "Go back to his hometown for a quiet life instead of competing in a big city"
      ],
      "c": 2
    }
  ],
  "grammar": [
    {
      "p": "与其…不如…",
      "e": "'Rather than A, better B' — compares two options and prefers the second: 与其在大城市继续竞争，不如回老家。",
      "x": "与其在家等消息，不如自己去问清楚。— Rather than waiting at home for news, it's better to go ask and find out yourself."
    },
    {
      "p": "不是…而是…",
      "e": "'Not A, but B' — corrects an assumption: 这不是懒，而是一种清醒。",
      "x": "他不去不是因为忙，而是因为不想去。— He isn't going not because he's busy, but because he doesn't want to."
    }
  ]
}
